rubick-0.0.4.data/scripts/rubick
rubick_pkg/__init__.py
rubick_pkg/config.yaml
rubick_pkg/constants.py
rubick_pkg/context.py
rubick_pkg/responses.py
rubick_pkg/rubick.py
rubick_pkg/commands/__init__.py
rubick_pkg/commands/project:create.py
rubick_pkg/commands/scaffolds:list.py
rubick_pkg/commands/scaffolds:update.py
rubick_pkg/utils/__init__.py
rubick_pkg/utils/dir.py
rubick_pkg/utils/file.py
rubick_pkg/utils/logger.py
rubick_pkg/utils/try_execpt.py
rubick-0.0.4.dist-info/LICENSE
rubick-0.0.4.dist-info/METADATA
rubick-0.0.4.dist-info/WHEEL
rubick-0.0.4.dist-info/top_level.txt
rubick-0.0.4.dist-info/RECORD
